trainyard/__init__.py
trainyard/track.py
trainyard/engine/__init__.py
trainyard/engine/cluster.py
trainyard/engine/local.py
trainyard/engine/runhouse.py
trainyard/engine/utils.py
trainyard/engine_v2/engine.py
trainyard/engine_v2/runhouse.py
trainyard/tasks/__init__.py
trainyard/tasks/tasks.py
trainyard/trainer/__init__.py
trainyard/trainer/base.py
trainyard/workflow/__init__.py
trainyard/workflow/prefect.py
trainyard/workflow/workflow.py
trainyard-0.0.3.dist-info/LICENSE
trainyard-0.0.3.dist-info/METADATA
trainyard-0.0.3.dist-info/WHEEL
trainyard-0.0.3.dist-info/top_level.txt
trainyard-0.0.3.dist-info/RECORD
