Metadata-Version: 2.1
Name: trainyard
Version: 0.0.3
Author-email: Shyam Sudhakaran <shyamsnair@protonmail.com>
Requires-Python: >=3.8
License-File: LICENSE
Requires-Dist: runhouse
Provides-Extra: dev
